zlkpo/__init__.py
zlkpo/kptv.py
zlkpo-0.1.1.dist-info/METADATA
zlkpo-0.1.1.dist-info/WHEEL
zlkpo-0.1.1.dist-info/top_level.txt
zlkpo-0.1.1.dist-info/zip-safe
zlkpo-0.1.1.dist-info/RECORD
